{
    "articles": [
        {
            "Title": "OpenBSD/ARM64 on Hetzner Cloud",
            "Link": "https://www.undeadly.org/cgi?action=article;sid=20230921073556",
            "Votes": "49 points"
        },
        {
            "Title": "Terry Tao's generals (2012)",
            "Link": "https://web.math.princeton.edu/generals/tao_terence",
            "Votes": "222 points"
        },
        {
            "Title": "Introduction to Linux interfaces for virtual networking (2018)",
            "Link": "https://developers.redhat.com/blog/2018/10/22/introduction-to-linux-interfaces-for-virtual-networking",
            "Votes": "95 points"
        },
        {
            "Title": "Install Windows the Arch Linux Way",
            "Link": "https://christitus.com/install-windows-the-arch-linux-way/",
            "Votes": "193 points"
        },
        {
            "Title": "Erlang/OTP 26.1 Released",
            "Link": "https://erlangforums.com/t/erlang-otp-26-1-released/2886",
            "Votes": "34 points"
        },
        {
            "Title": "MongoDB\u2019s New Query Engine",
            "Link": "https://laplab.me/posts/inside-new-query-engine-of-mongodb/",
            "Votes": "14 points"
        },
        {
            "Title": "UK Parliament undermined the privacy, security, freedom of all internet users",
            "Link": "https://www.eff.org/deeplinks/2023/09/today-uk-parliament-undermined-privacy-security-and-freedom-all-internet-users",
            "Votes": "314 points"
        },
        {
            "Title": "Car allergic to vanilla ice cream (2000)",
            "Link": "http://www.cs.cmu.edu/~wkw/humour/carproblems.txt",
            "Votes": "1416 points"
        },
        {
            "Title": "India's biggest tech centers named as cyber crime hotspots",
            "Link": "https://www.theregister.com/2023/09/21/india_cybercrime_trends_report/",
            "Votes": "18 points"
        },
        {
            "Title": "Harlequin: DuckDB IDE for the terminal",
            "Link": "https://harlequin.sh/",
            "Votes": "271 points"
        },
        {
            "Title": "Grouping digits in SQL",
            "Link": "http://peter.eisentraut.org/blog/2023/09/20/grouping-digits-in-sql",
            "Votes": "49 points"
        },
        {
            "Title": "How Equifax Was Breached in 2017",
            "Link": "https://blog.0x7d0.dev/history/how-equifax-was-breached-in-2017/",
            "Votes": "123 points"
        },
        {
            "Title": "How Container Networking Works: Practical Explanation",
            "Link": "https://iximiuz.com/en/posts/container-networking-is-simple/",
            "Votes": "37 points"
        },
        {
            "Title": "Cache headers could probably be more aggressive",
            "Link": "https://www.macarthur.me/posts/more-aggressive-cache-headers",
            "Votes": "44 points"
        },
        {
            "Title": "NASA\u2019s New Shortcut to Fusion Power (2022)",
            "Link": "https://spectrum.ieee.org/lattice-confinement-fusion",
            "Votes": "27 points"
        },
        {
            "Title": "Fine-grained caching strategies of dynamic queries",
            "Link": "https://jensrantil.github.io/posts/fast-aggregate-queries-on-dynamic-data/",
            "Votes": "56 points"
        },
        {
            "Title": "How to evaluate a product roadmap, for engineers",
            "Link": "https://stephen.fm/how-to-evaluate-a-product-roadmap/",
            "Votes": "111 points"
        },
        {
            "Title": "Creating a fake Indian cricket league",
            "Link": "https://www.si.com/betting/2023/09/15/fake-indian-cricket-league-daily-cover",
            "Votes": "20 points"
        },
        {
            "Title": "Meticulous: An FPGA-Based Main Memory Emulator for System Software Studies",
            "Link": "https://arxiv.org/abs/2309.06565",
            "Votes": "37 points"
        },
        {
            "Title": "Total cholesterol and mortality by sex and age:study of 12.8M adults",
            "Link": "https://www.nature.com/articles/s41598-018-38461-y",
            "Votes": "43 points"
        },
        {
            "Title": "Show HN: Mana Pool \u2013 Market for Magic Cards",
            "Link": "https://manapool.com/",
            "Votes": "51 points"
        },
        {
            "Title": "Is Fortran easier to optimize than C for heavy calculations?",
            "Link": "https://stackoverflow.com/questions/146159/is-fortran-easier-to-optimize-than-c-for-heavy-calculations",
            "Votes": "114 points"
        },
        {
            "Title": "Linux gives up on 6-year LTS kernels, says they\u2019re too much work",
            "Link": "https://arstechnica.com/gadgets/2023/09/linux-gives-up-on-6-year-lts-thats-fine-for-pcs-bad-for-android/",
            "Votes": "3 points"
        },
        {
            "Title": "Toyota Research claims breakthrough in teaching robots new behaviors",
            "Link": "https://www.tri.global/news/toyota-research-institute-unveils-breakthrough-teaching-robots-new-behaviors",
            "Votes": "198 points"
        },
        {
            "Title": "Strong arrows: a new approach to gradual typing",
            "Link": "https://elixir-lang.org/blog/2023/09/20/strong-arrows-gradual-typing/",
            "Votes": "346 points"
        },
        {
            "Title": "Organic Maps: An open-source maps app that doesn't suck",
            "Link": "https://hardfault.life/p/organic-maps-review",
            "Votes": "3 points"
        },
        {
            "Title": "Show HN: ElectricSQL, Postgres to SQLite active-active sync for local-first apps",
            "Link": "https://electric-sql.com/",
            "Votes": "60 points"
        },
        {
            "Title": "New study disproves Leonardo da Vinci's 'rule of trees'",
            "Link": "https://phys.org/news/2023-09-leonardo-da-vinci-trees.html",
            "Votes": "167 points"
        }
    ]
}